LICENSE
README.md
pyproject.toml
src/samsam/__init__.py
src/samsam/acf.py
src/samsam/logprior.py
src/samsam.egg-info/PKG-INFO
src/samsam.egg-info/SOURCES.txt
src/samsam.egg-info/dependency_links.txt
src/samsam.egg-info/requires.txt
src/samsam.egg-info/top_level.txt
tests/test_samsam.py