Metadata-Version: 2.4
Name: samsam
Version: 1.0.7
Summary: Scaled Adaptive Metropolis SAMpler
Author-email: Jean-Baptiste Delisle <jean-baptiste.delisle@unige.ch>
Project-URL: Homepage, https://gitlab.unige.ch/delisle/samsam
Project-URL: Issues, https://gitlab.unige.ch/delisle/samsam/-/issues
Classifier: Programming Language :: Python :: 3
Classifier: License :: OSI Approved :: European Union Public Licence 1.2 (EUPL 1.2)
Classifier: Operating System :: OS Independent
Requires-Python: >=3.8
License-File: LICENSE
Requires-Dist: numpy>=1.16
Requires-Dist: scipy>=1.2
Dynamic: license-file
